licscan/__init__.py
licscan/default_lic_list.py
licscan/main.py
licscan/unthreaded.py
LicScan-1.0.1.dist-info/LICENSE
LicScan-1.0.1.dist-info/METADATA
LicScan-1.0.1.dist-info/WHEEL
LicScan-1.0.1.dist-info/entry_points.txt
LicScan-1.0.1.dist-info/top_level.txt
LicScan-1.0.1.dist-info/RECORD
