Metadata-Version: 2.1
Name: LicScan
Version: 1.0.1
Summary: Check your requirements to make sure your requirements have the correct licenses.
Home-page: https://github.com/fakerybakery/licscan
Author: GitHub @fakerybakery
Author-email: me@mrfake.name
License: UPL
Platform: Any
Classifier: Programming Language :: Python :: 3
Classifier: Operating System :: OS Independent
Requires-Python: >=3.9
License-File: LICENSE
Requires-Dist: requirements-parser
Requires-Dist: tqdm
